setup.cfg
setup.py
rino/__init__.py
rino/browse.py
rino/cli.py
rino/config.py
rino/git.py
rino/initialize.py
rino/login.py
rino/notebook.py
rino/remote.py
rino/utils.py
rinocloud_cli.egg-info/PKG-INFO
rinocloud_cli.egg-info/SOURCES.txt
rinocloud_cli.egg-info/dependency_links.txt
rinocloud_cli.egg-info/entry_points.txt
rinocloud_cli.egg-info/requires.txt
rinocloud_cli.egg-info/top_level.txt