Metadata-Version: 1.1
Name: rinocloud-cli
Version: 0.0.1
Summary: Rinocloud python bindings
Home-page: https://github.com/rinocloud/rinocloud-python
Author: Eoin Murray
Author-email: eoin@rinocloud.com
License: UNKNOWN
Download-URL: https://github.com/rinocloud/rinocloud-python/tarball/0.1
Keywords: rinocloud,data,api
Platform: UNKNOWN
